asgi_correlation_id/__init__.py
asgi_correlation_id/context.py
asgi_correlation_id/extensions/__init__.py
asgi_correlation_id/extensions/celery.py
asgi_correlation_id/extensions/sentry.py
asgi_correlation_id/log_filters.py
asgi_correlation_id/middleware.py
asgi_correlation_id/py.typed
asgi_correlation_id-4.3.2.dist-info/LICENSE
asgi_correlation_id-4.3.2.dist-info/METADATA
asgi_correlation_id-4.3.2.dist-info/WHEEL
asgi_correlation_id-4.3.2.dist-info/RECORD
